{
    "forge_marker": 1,
    "defaults": {"model": "polycraft:inventories/condenser.obj"},
    "variants": {
        "normal": [{
			"transform": {
				"translation": [0.0, 0.0, 1.0]
			}
		}],
        "inventory": [{
            "transform": {
                "thirdperson": {
                    "translation": [0.0, 0.0, 0.30],
                    "rotation": [ { "y": 0}, {"x": 90}, {"z": 180} ],
                    "scale": 1.0
                },
                "gui": {
					"translation": [0.0,0.15,1.0],
					"scale": 2.0
                }
            }
        }]
    }
}