{
    "forge_marker": 1,
    "defaults": {"model": "polycraft:inventories/gaslamp.obj"},
    "variants": {
        "normal": [{
			"transform": {
				"translation": [0.0, 0.0, 0.0],
				"rotation": [ { "y": 90}, {"x": 0}, {"z": 0} ],
				"scale": [ 1.0, 1.0, 1.0 ]
			}
		}],
        "inventory": [{
            "transform": {
			    "firstperson": {
                    "translation": [0.0, 0.0, 0.0],
                    "rotation": [ { "y": 0}, {"x": 0}, {"z": 0} ],
                    "scale": [ 0.375, 0.375, 0.375 ]
                },
                "thirdperson": {
                    "translation": [0.0, 0.2,-0.20],
                    "rotation": [ { "y": 315}, {"x": 30}, {"z":180} ],
                    "scale": [ 0.3, 0.3, 0.3 ]
                },
                "gui": {
					"translation": [0.00,-0.25,0.00],
					"scale": 0.55
                }
            }
        }],
        "facing=north": { "model": "polycraft:inventories/gaslamp.obj", "y": 90 },
        "facing=south": { "model": "polycraft:inventories/gaslamp.obj", "y": 270 },
        "facing=west":  { "model": "polycraft:inventories/gaslamp.obj", "y": 0 },
        "facing=east":  { "model": "polycraft:inventories/gaslamp.obj", "y": 180 }
    }
}